vehicle_form_validator/__init__.py
vehicle_form_validator/validators.py
vehicle_form_validator-1.0.0.dist-info/LICENSE
vehicle_form_validator-1.0.0.dist-info/METADATA
vehicle_form_validator-1.0.0.dist-info/WHEEL
vehicle_form_validator-1.0.0.dist-info/top_level.txt
vehicle_form_validator-1.0.0.dist-info/RECORD
