Metadata-Version: 2.1
Name: vehicle_form_validator
Version: 1.0.0
Summary: A library to validate vehicle and user details
Home-page: https://github.com/rhegisan/vehicle_form_validator
Author: Rhegisan Jebas
Author-email: rhegisanjebas71@gmail.com
Classifier: Programming Language :: Python :: 3
Classifier: License :: OSI Approved :: MIT License
Classifier: Operating System :: OS Independent
Requires-Python: >=3.7
License-File: LICENSE
